[
   {
      "beauty": 0,
      "age": 55,
      "gender": "F",
      "mood": "happy",
      "file": "http://idowebsites.ch/sensibleData/images/0-55-F-happy-1435348032.jpg"
   },
   {
      "beauty": 0,
      "age": 26,
      "gender": "M",
      "mood": "disgust",
      "file": "http://idowebsites.ch/sensibleData/images/00-26-M-disgust-1434460951.jpg"
   },
   {
      "beauty": 0,
      "age": 29,
      "gender": "M",
      "mood": "PENSIVE",
      "file": "http://idowebsites.ch/sensibleData/images/00-29-M-PENSIVE-1434695565.jpg"
   },
   {
      "beauty": 4,
      "age": 41,
      "gender": "M",
      "mood": "confused",
      "file": "http://idowebsites.ch/sensibleData/images/04-41-M-confused-1434460395.jpg"
   },
   {
      "beauty": 7,
      "age": 37,
      "gender": "MALE",
      "mood": "confused",
      "file": "http://idowebsites.ch/sensibleData/images/07-37-MALE-confused-1434453371.jpg"
   },
   {
      "beauty": 9,
      "age": 42,
      "gender": "M",
      "mood": "NEUTRAL",
      "file": "http://idowebsites.ch/sensibleData/images/09-42-M-NEUTRAL-1434696790.jpg"
   },
   {
      "beauty": 9,
      "age": 43,
      "gender": "MALE",
      "mood": "happy",
      "file": "http://idowebsites.ch/sensibleData/images/09-43-MALE-happy-1434447769.jpg"
   },
   {
      "beauty": 1,
      "age": 23,
      "gender": "M",
      "mood": "sad",
      "file": "http://idowebsites.ch/sensibleData/images/1-23-M-sad-1446807993.jpg"
   },
   {
      "beauty": 1,
      "age": 35,
      "gender": "M",
      "mood": "surprised",
      "file": "http://idowebsites.ch/sensibleData/images/1-35-M-surprised-1443117099.jpg"
   },
   {
      "beauty": 10,
      "age": 39,
      "gender": "M",
      "mood": "CONFUSED",
      "file": "http://idowebsites.ch/sensibleData/images/10-39-M-CONFUSED-1434645479.jpg"
   },
   {
      "beauty": 11,
      "age": 23,
      "gender": "M",
      "mood": "calm",
      "file": "http://idowebsites.ch/sensibleData/images/11-23-M-calm-1446808227.jpg"
   },
   {
      "beauty": 11,
      "age": 39,
      "gender": "F",
      "mood": "happy",
      "file": "http://idowebsites.ch/sensibleData/images/11-39-F-happy-1443118717.jpg"
   },
   {
      "beauty": 12,
      "age": 27,
      "gender": "MALE",
      "mood": "sad",
      "file": "http://idowebsites.ch/sensibleData/images/12-27-MALE-sad-1434316449.jpg"
   },
   {
      "beauty": 12,
      "age": 50,
      "gender": "F",
      "mood": "happy",
      "file": "http://idowebsites.ch/sensibleData/images/12-50-F-happy-1435333290.jpg"
   },
   {
      "beauty": 13,
      "age": 38,
      "gender": "MALE",
      "mood": "calm",
      "file": "http://idowebsites.ch/sensibleData/images/13-38-MALE-calm-1434316410.jpg"
   },
   {
      "beauty": 19,
      "age": 36,
      "gender": "M",
      "mood": "happy",
      "file": "http://idowebsites.ch/sensibleData/images/19-36-M-happy-1443101052.jpg"
   },
   {
      "beauty": 21,
      "age": 35,
      "gender": "F",
      "mood": "happy",
      "file": "http://idowebsites.ch/sensibleData/images/21-35-F-happy-1435333110.jpg"
   },
   {
      "beauty": 22,
      "age": 34,
      "gender": "M",
      "mood": "happy",
      "file": "http://idowebsites.ch/sensibleData/images/22-34-M-happy-1434725528.jpg"
   },
   {
      "beauty": 22,
      "age": 36,
      "gender": "F",
      "mood": "happy",
      "file": "http://idowebsites.ch/sensibleData/images/22-36-F-happy-1435348691.jpg"
   },
   {
      "beauty": 23,
      "age": 28,
      "gender": "M",
      "mood": "happy",
      "file": "http://idowebsites.ch/sensibleData/images/23-28-M-happy-1434462332.jpg"
   },
   {
      "beauty": 27,
      "age": 32,
      "gender": "FEMALE",
      "mood": "confused",
      "file": "http://idowebsites.ch/sensibleData/images/27-32-FEMALE-confused-1434394243.jpg"
   },
   {
      "beauty": 3,
      "age": 27,
      "gender": "M",
      "mood": "calm",
      "file": "http://idowebsites.ch/sensibleData/images/3-27-M-calm-1446807793.jpg"
   },
   {
      "beauty": 3,
      "age": 82,
      "gender": "M",
      "mood": "happy",
      "file": "http://idowebsites.ch/sensibleData/images/3-82-M-happy-1435348417.jpg"
   },
   {
      "beauty": 32,
      "age": 36,
      "gender": "M",
      "mood": "CONFUSED",
      "file": "http://idowebsites.ch/sensibleData/images/32-36-M-CONFUSED-1434697281.jpg"
   },
   {
      "beauty": 33,
      "age": 32,
      "gender": "FEMALE",
      "mood": "confused",
      "file": "http://idowebsites.ch/sensibleData/images/33-32-FEMALE-confused-1434382289.jpg"
   },
   {
      "beauty": 35,
      "age": 37,
      "gender": "MALE",
      "mood": "confused",
      "file": "http://idowebsites.ch/sensibleData/images/35-37-MALE-confused-1434454466.jpg"
   },
   {
      "beauty": 38,
      "age": 23,
      "gender": "F",
      "mood": "NONE",
      "file": "http://idowebsites.ch/sensibleData/images/38-23-F-NONE-1434642522.jpg"
   },
   {
      "beauty": 39,
      "age": 31,
      "gender": "M",
      "mood": "calm",
      "file": "http://idowebsites.ch/sensibleData/images/39-31-M-calm-1435350080.jpg"
   },
   {
      "beauty": 43,
      "age": 26,
      "gender": "M",
      "mood": "happy",
      "file": "http://idowebsites.ch/sensibleData/images/43-26-M-happy-1443114695.jpg"
   },
   {
      "beauty": 44,
      "age": 27,
      "gender": "F",
      "mood": "happy",
      "file": "http://idowebsites.ch/sensibleData/images/44-27-F-happy-1443115175.jpg"
   },
   {
      "beauty": 44,
      "age": 30,
      "gender": "M",
      "mood": "CONFUSED",
      "file": "http://idowebsites.ch/sensibleData/images/44-30-M-CONFUSED-1443116176.jpg"
   },
   {
      "beauty": 44,
      "age": 30,
      "gender": "M",
      "mood": "CONFUSED",
      "file": "http://idowebsites.ch/sensibleData/images/44-30-M-CONFUSED-1443116347.jpg"
   },
   {
      "beauty": 45,
      "age": 27,
      "gender": "F",
      "mood": "happy",
      "file": "http://idowebsites.ch/sensibleData/images/45-27-F-happy-1443119012.jpg"
   },
   {
      "beauty": 48,
      "age": 50,
      "gender": "MALE",
      "mood": "confused",
      "file": "http://idowebsites.ch/sensibleData/images/48-50-MALE-confused-1434385245.jpg"
   },
   {
      "beauty": 49,
      "age": 22,
      "gender": "M",
      "mood": "PENSIVE",
      "file": "http://idowebsites.ch/sensibleData/images/49-22-M-PENSIVE-1434693000.jpg"
   },
   {
      "beauty": 5,
      "age": 57,
      "gender": "M",
      "mood": "CONFUSED",
      "file": "http://idowebsites.ch/sensibleData/images/5-57-M-CONFUSED-1435225050.jpg"
   },
   {
      "beauty": 50,
      "age": 27,
      "gender": "M",
      "mood": "happy",
      "file": "http://idowebsites.ch/sensibleData/images/50-27-M-happy-1446796500.jpg"
   },
   {
      "beauty": 52,
      "age": 29,
      "gender": "F",
      "mood": "calm",
      "file": "http://idowebsites.ch/sensibleData/images/52-29-F-calm-1443115435.jpg"
   },
   {
      "beauty": 53,
      "age": 42,
      "gender": "M",
      "mood": "CONFUSED",
      "file": "http://idowebsites.ch/sensibleData/images/53-42-M-CONFUSED-1446732365.jpg"
   },
   {
      "beauty": 55,
      "age": 23,
      "gender": "M",
      "mood": "sad",
      "file": "http://idowebsites.ch/sensibleData/images/55-23-M-sad-1443089956.jpg"
   },
   {
      "beauty": 55,
      "age": 26,
      "gender": "MALE",
      "mood": "NONE",
      "file": "http://idowebsites.ch/sensibleData/images/55-26-MALE-NONE-1434384564.jpg"
   },
   {
      "beauty": 55,
      "age": 27,
      "gender": "F",
      "mood": "happy",
      "file": "http://idowebsites.ch/sensibleData/images/55-27-F-happy-1435349395.jpg"
   },
   {
      "beauty": 55,
      "age": 30,
      "gender": "M",
      "mood": "CONFUSED",
      "file": "http://idowebsites.ch/sensibleData/images/55-30-M-CONFUSED-1446732938.jpg"
   },
   {
      "beauty": 55,
      "age": 34,
      "gender": "M",
      "mood": "CONFUSED",
      "file": "http://idowebsites.ch/sensibleData/images/55-34-M-CONFUSED-1443096463.jpg"
   },
   {
      "beauty": 57,
      "age": 25,
      "gender": "FEMALE",
      "mood": "happy",
      "file": "http://idowebsites.ch/sensibleData/images/57-25-FEMALE-happy-1434452020.jpg"
   },
   {
      "beauty": 6,
      "age": 23,
      "gender": "M",
      "mood": "sad",
      "file": "http://idowebsites.ch/sensibleData/images/6-23-M-sad-1446806733.jpg"
   },
   {
      "beauty": 61,
      "age": 23,
      "gender": "FEMALE",
      "mood": "happy",
      "file": "http://idowebsites.ch/sensibleData/images/61-23-FEMALE-happy-1434383884.jpg"
   },
   {
      "beauty": 61,
      "age": 36,
      "gender": "M",
      "mood": "happy",
      "file": "http://idowebsites.ch/sensibleData/images/61-36-M-happy-1434641732.jpg"
   },
   {
      "beauty": 62,
      "age": 20,
      "gender": "MALE",
      "mood": "confused",
      "file": "http://idowebsites.ch/sensibleData/images/62-20-MALE-confused-1434454087.jpg"
   },
   {
      "beauty": 64,
      "age": 28,
      "gender": "F",
      "mood": "ABSENT",
      "file": "http://idowebsites.ch/sensibleData/images/64-28-F-ABSENT-1434625998.jpg"
   },
   {
      "beauty": 68,
      "age": 28,
      "gender": "F",
      "mood": "happy",
      "file": "http://idowebsites.ch/sensibleData/images/68-28-F-happy-1435349700.jpg"
   },
   {
      "beauty": 7,
      "age": 47,
      "gender": "M",
      "mood": "happy",
      "file": "http://idowebsites.ch/sensibleData/images/7-47-M-happy-1443100712.jpg"
   },
   {
      "beauty": 70,
      "age": 35,
      "gender": "MALE",
      "mood": "confused",
      "file": "http://idowebsites.ch/sensibleData/images/70-35-MALE-confused-1434382776.jpg"
   },
   {
      "beauty": 71,
      "age": 29,
      "gender": "MALE",
      "mood": "confused",
      "file": "http://idowebsites.ch/sensibleData/images/71-29-MALE-confused-1434313756.jpg"
   },
   {
      "beauty": 72,
      "age": 26,
      "gender": "M",
      "mood": "happy",
      "file": "http://idowebsites.ch/sensibleData/images/72-26-M-happy-1434460650.jpg"
   },
   {
      "beauty": 73,
      "age": 23,
      "gender": "F",
      "mood": "surprised",
      "file": "http://idowebsites.ch/sensibleData/images/73-23-F-surprised-1443115975.jpg"
   },
   {
      "beauty": 73,
      "age": 34,
      "gender": "F",
      "mood": "happy",
      "file": "http://idowebsites.ch/sensibleData/images/73-34-F-happy-1435350571.jpg"
   },
   {
      "beauty": 73,
      "age": 41,
      "gender": "M",
      "mood": "happy",
      "file": "http://idowebsites.ch/sensibleData/images/73-41-M-happy-1434641514.jpg"
   },
   {
      "beauty": 77,
      "age": 16,
      "gender": "F",
      "mood": "happy",
      "file": "http://idowebsites.ch/sensibleData/images/77-16-F-happy-1443115644.jpg"
   },
   {
      "beauty": 77,
      "age": 23,
      "gender": "F",
      "mood": "happy",
      "file": "http://idowebsites.ch/sensibleData/images/77-23-F-happy-1443119149.jpg"
   },
   {
      "beauty": 79,
      "age": 16,
      "gender": "F",
      "mood": "happy",
      "file": "http://idowebsites.ch/sensibleData/images/79-16-F-happy-1435160823.jpg"
   },
   {
      "beauty": 8,
      "age": 30,
      "gender": "F",
      "mood": "happy",
      "file": "http://idowebsites.ch/sensibleData/images/8-30-F-happy-1435158202.jpg"
   },
   {
      "beauty": 8,
      "age": 49,
      "gender": "F",
      "mood": "happy",
      "file": "http://idowebsites.ch/sensibleData/images/8-49-F-happy-1446805676.jpg"
   },
   {
      "beauty": 80,
      "age": 27,
      "gender": "FEMALE",
      "mood": "happy",
      "file": "http://idowebsites.ch/sensibleData/images/80-27-FEMALE-happy-1434394357.jpg"
   },
   {
      "beauty": 82,
      "age": 26,
      "gender": "MALE",
      "mood": "happy",
      "file": "http://idowebsites.ch/sensibleData/images/82-26-MALE-happy-1434448283.jpg"
   },
   {
      "beauty": 82,
      "age": 41,
      "gender": "F",
      "mood": "confused",
      "file": "http://idowebsites.ch/sensibleData/images/82-41-F-confused-1434460048.jpg"
   },
   {
      "beauty": 83,
      "age": 21,
      "gender": "FEMALE",
      "mood": "confused",
      "file": "http://idowebsites.ch/sensibleData/images/83-21-FEMALE-confused-1434453151.jpg"
   },
   {
      "beauty": 83,
      "age": 33,
      "gender": "F",
      "mood": "happy",
      "file": "http://idowebsites.ch/sensibleData/images/83-33-F-happy-1435349053.jpg"
   },
   {
      "beauty": 84,
      "age": 27,
      "gender": "F",
      "mood": "happy",
      "file": "http://idowebsites.ch/sensibleData/images/84-27-F-happy-1443117607.jpg"
   },
   {
      "beauty": 84,
      "age": 27,
      "gender": "F",
      "mood": "happy",
      "file": "http://idowebsites.ch/sensibleData/images/84-27-F-happy-1443117902.jpg"
   },
   {
      "beauty": 85,
      "age": 39,
      "gender": "M",
      "mood": "surprised",
      "file": "http://idowebsites.ch/sensibleData/images/85-39-M-surprised-1434725764.jpg"
   },
   {
      "beauty": 86,
      "age": 21,
      "gender": "FEMALE",
      "mood": "sad",
      "file": "http://idowebsites.ch/sensibleData/images/86-21-FEMALE-sad-1434316380.jpg"
   },
   {
      "beauty": 86,
      "age": 42,
      "gender": "MALE",
      "mood": "angry",
      "file": "http://idowebsites.ch/sensibleData/images/86-42-MALE-angry-1434394315.jpg"
   },
   {
      "beauty": 89,
      "age": 23,
      "gender": "M",
      "mood": "happy",
      "file": "http://idowebsites.ch/sensibleData/images/89-23-M-happy-1446736088.jpg"
   },
   {
      "beauty": 90,
      "age": 33,
      "gender": "M",
      "mood": "calm",
      "file": "http://idowebsites.ch/sensibleData/images/90-33-M-calm-1446729245.jpg"
   },
   {
      "beauty": 90,
      "age": 39,
      "gender": "M",
      "mood": "calm",
      "file": "http://idowebsites.ch/sensibleData/images/90-39-M-calm-1446805219.jpg"
   },
   {
      "beauty": 92,
      "age": 21,
      "gender": "F",
      "mood": "happy",
      "file": "http://idowebsites.ch/sensibleData/images/92-21-F-happy-1443036582.jpg"
   },
   {
      "beauty": 92,
      "age": 21,
      "gender": "F",
      "mood": "happy",
      "file": "http://idowebsites.ch/sensibleData/images/92-21-F-happy-1443080007.jpg"
   },
   {
      "beauty": 95,
      "age": 32,
      "gender": "M",
      "mood": "confused",
      "file": "http://idowebsites.ch/sensibleData/images/95-32-M-confused-1434463341.jpg"
   },
   {
      "beauty": 99,
      "age": 36,
      "gender": "M",
      "mood": "calm",
      "file": "http://idowebsites.ch/sensibleData/images/99-36-M-calm-1434642095.jpg"
   }
]
